financial_planner/__init__.py
financial_planner-0.0.2.dist-info/LICENSE
financial_planner-0.0.2.dist-info/WHEEL
financial_planner-0.0.2.dist-info/METADATA
financial_planner-0.0.2.dist-info/RECORD
