Metadata-Version: 2.1
Name: financial_planner
Version: 0.0.2
Summary: Financial Planner
Home-page: https://github.com/AstrocyteResearch/financial-planner
License: UNKNOWN
Author: Astrocyte Research, Inc
Author-email: support@astrocyte.io
Classifier: License :: OSI Approved :: Apache Software License
